googlecontroller/__init__.py
googlecontroller-6.dist-info/LICENSE
googlecontroller-6.dist-info/METADATA
googlecontroller-6.dist-info/WHEEL
googlecontroller-6.dist-info/entry_points.txt
googlecontroller-6.dist-info/top_level.txt
googlecontroller-6.dist-info/RECORD
