Metadata-Version: 2.1
Name: googlecontroller
Version: 6
Summary: control your google home
Home-page: https://github.com/dray-cyber/googlecontroller
Author: dray-cyber
Author-email: testerforpyt123@gmail.com
License: MIT
Platform: UNKNOWN
Classifier: License :: OSI Approved :: MIT License
Classifier: Programming Language :: Python :: 3
Classifier: Programming Language :: Python :: 3.9
License-File: LICENSE
Requires-Dist: requests
Requires-Dist: pychromecast
Requires-Dist: pyngrok
